hnmf/__init__.py
hnmf/helpers.py
hnmf/model.py
hnmf/progress_tree.py
hnmf-0.3.2.dist-info/METADATA
hnmf-0.3.2.dist-info/WHEEL
hnmf-0.3.2.dist-info/RECORD
