Metadata-Version: 2.4
Name: hNMF
Version: 0.3.2
Summary: Hierarchical NMF
Project-URL: Homepage, https://github.com/estasney/hNMF
Author-email: Eric Stasney <estasney@users.noreply.github.com>
License: MIT
Classifier: License :: OSI Approved :: MIT License
Classifier: Programming Language :: Python
Classifier: Programming Language :: Python :: 3.12
Requires-Python: >=3.12
Requires-Dist: networkx>=2.3
Requires-Dist: numpy>=1.24.4
Requires-Dist: rich>=14.2.0
Requires-Dist: scikit-learn>=1.3.2
Requires-Dist: scipy>=1.10.1
